{
  "tiles" : [ {
    "scaleFactors" : [ 32, 16, 8, 4, 2, 1 ],
    "width" : 1024,
    "height" : 1024
  } ],
  "protocol" : "http://iiif.io/api/image",
  "sizes" : [ {
    "width" : 59,
    "height" : 30
  }, {
    "width" : 117,
    "height" : 60
  }, {
    "width" : 234,
    "height" : 120
  }, {
    "width" : 468,
    "height" : 240
  }, {
    "width" : 936,
    "height" : 479
  }, {
    "width" : 1872,
    "height" : 958
  } ],
  "profile" : "http://iiif.io/api/image/2/level0.json",
  "width" : 1872,
  "@id" : "https://leonardol.github.io/Test/images/screenshot1",
  "@context" : "http://iiif.io/api/image/2/context.json",
  "height" : 958
}